simple_injector/__init__.py
simple_injector/__version__.py
simple_injector/simple-injector.py
simple_injector/simple_injector.py
simple_injector-1.1.2.dist-info/LICENSE.txt
simple_injector-1.1.2.dist-info/METADATA
simple_injector-1.1.2.dist-info/WHEEL
simple_injector-1.1.2.dist-info/top_level.txt
simple_injector-1.1.2.dist-info/RECORD
