Metadata-Version: 2.1
Name: simple-injector
Version: 1.1.2
Summary: Dependency Injection made simple.
Home-page: https://github.com/pvsfair/simple-injector
Author: Paulo Victor Alvares
Author-email: pvsfair@gmail.com
License: GPLv3
Platform: UNKNOWN
Classifier: License :: OSI Approved :: GNU General Public License v3 (GPLv3)
Classifier: Programming Language :: Python :: 3
